luffa_bot/__init__.py
luffa_bot/_globals.py
luffa_bot/cli.py
luffa_bot/client.py
luffa_bot/exceptions.py
luffa_bot/models.py
luffa_bot/polling.py
luffa_bot/py.typed
luffa_bot_python_sdk-0.1.1.dist-info/licenses/LICENSE
luffa_bot_python_sdk-0.1.1.dist-info/METADATA
luffa_bot_python_sdk-0.1.1.dist-info/WHEEL
luffa_bot_python_sdk-0.1.1.dist-info/entry_points.txt
luffa_bot_python_sdk-0.1.1.dist-info/top_level.txt
luffa_bot_python_sdk-0.1.1.dist-info/RECORD
