Metadata-Version: 2.4
Name: luffa-bot-python-sdk
Version: 0.1.1
Summary: Async Python SDK for building bots on the Luffa messaging platform
Home-page: https://github.com/sabma-labs/luffa-bot-python-sdk
Author: Niraj Kulkarni (Sabma Labs, University of Surrey)
Author-email: niraj.kulkarni@luffa.im
License: Apache License 2.0
Classifier: Programming Language :: Python :: 3
Classifier: License :: OSI Approved :: Apache Software License
Classifier: Operating System :: OS Independent
Classifier: Topic :: Internet :: WWW/HTTP
Classifier: Framework :: AsyncIO
Classifier: Typing :: Typed
Requires-Python: >=3.9
License-File: LICENSE
Requires-Dist: httpx>=0.27
Requires-Dist: anyio>=4.0
Provides-Extra: dev
Requires-Dist: pytest>=8; extra == "dev"
Requires-Dist: pytest-asyncio>=0.23; extra == "dev"
Requires-Dist: respx>=0.21; extra == "dev"
Requires-Dist: ruff>=0.5; extra == "dev"
Requires-Dist: mypy>=1.7; extra == "dev"
Dynamic: license-file
